pocketsocket/__init__.py
pocketsocket/__main__.py
pocketsocket/client.py
pocketsocket/echo.py
pocketsocket/example.py
pocketsocket/http.py
pocketsocket/logger.py
pocketsocket/mixins.py
pocketsocket/options.py
pocketsocket/reply.py
pocketsocket/server.py
pocketsocket/settings.py
pocketsocket/states.py
pocketsocket/utils.py
pocketsocket/ws.py
pocketsocket-0.4.1.dist-info/DESCRIPTION.rst
pocketsocket-0.4.1.dist-info/METADATA
pocketsocket-0.4.1.dist-info/RECORD
pocketsocket-0.4.1.dist-info/WHEEL
pocketsocket-0.4.1.dist-info/entry_points.txt
pocketsocket-0.4.1.dist-info/metadata.json
pocketsocket-0.4.1.dist-info/top_level.txt
