Metadata-Version: 2.0
Name: pocketsocket
Version: 0.4.1
Summary: Websocket server
Home-page: https://github.com/Strangemother/pocketsocket
Author: Jay Jagpal
Author-email: jay@strangemother.com
License: MIT
Keywords: websocket
Platform: UNKNOWN
Classifier: Development Status :: 3 - Alpha
Classifier: Intended Audience :: Developers
Classifier: Environment :: Web Environment
Classifier: License :: OSI Approved :: MIT License
Classifier: Programming Language :: Python :: 2.7
Provides-Extra: test
Requires-Dist: coverage; extra == 'test'
Requires-Dist: nosetests; extra == 'test'
Requires-Dist: smpq; extra == 'test'
Requires-Dist: websocket-client; extra == 'test'
